metabadger/__init__.py
metabadger/bin/__init__.py
metabadger/bin/cli.py
metabadger/bin/version.py
metabadger/command/__init__.py
metabadger/command/cloudwatch_metrics.py
metabadger/command/disable_metadata.py
metabadger/command/discover_metadata.py
metabadger/command/discover_role_usage.py
metabadger/command/harden_metadata.py
metabadger/shared/__init__.py
metabadger/shared/aws_auth.py
metabadger/shared/discover.py
metabadger/shared/modify.py
metabadger/shared/utils.py
metabadger/shared/validate.py
metabadger-0.1.11.dist-info/LICENSE
metabadger-0.1.11.dist-info/METADATA
metabadger-0.1.11.dist-info/WHEEL
metabadger-0.1.11.dist-info/entry_points.txt
metabadger-0.1.11.dist-info/top_level.txt
metabadger-0.1.11.dist-info/zip-safe
metabadger-0.1.11.dist-info/RECORD
