Metadata-Version: 2.1
Name: metabadger
Version: 0.1.11
Summary: AWS Security Tool that gives you the ability to analyze and harden the Instance Metadata Service. 
Home-page: https://github.com/salesforce/metabadger
Author: Ashish Patel
Author-email: ashishrpatel.io@gmail.com
License: UNKNOWN
Keywords: aws iam metadata roles policy policies privileges security
Platform: UNKNOWN
Classifier: Programming Language :: Python :: 3
Classifier: License :: OSI Approved :: MIT License
Classifier: Operating System :: OS Independent
Requires-Python: >=3.6
Requires-Dist: boto3
Requires-Dist: botocore
Requires-Dist: click
Requires-Dist: tabulate
Requires-Dist: colorama
Requires-Dist: pandas
